[{"name":"sql.active_record","payload":{"sql":"SELECT  \"agendas\".* FROM \"agendas\"  ORDER BY start_at desc LIMIT 10","name":"Agenda Load","connection_id":70356879922820,"statement_name":null,"binds":[],"line":11,"filename":"/Users/charlotte/HorsebackArchersOfHolland/app/controllers/api/v1/agendas.rb","method":"block (2 levels) in \u003cclass:Agendas\u003e"},"time":"2016-03-25T00:50:54.935+01:00","transaction_id":"e7342c9c16f2e51e04b9","end":"2016-03-25T00:50:54.937+01:00","children":[],"duration":1.4649999999999999}]